GC_Flask_FileUpload-0.5.0.dist-info/METADATA
GC_Flask_FileUpload-0.5.0.dist-info/RECORD
GC_Flask_FileUpload-0.5.0.dist-info/WHEEL
GC_Flask_FileUpload-0.5.0.dist-info/top_level.txt
flask_fileupload/__init__.py
flask_fileupload/engine.py
flask_fileupload/forms.py
flask_fileupload/views.py
flask_fileupload/static/css/zoom.css
flask_fileupload/storage/__init__.py
flask_fileupload/storage/gcstorage.py
flask_fileupload/storage/s3storage.py
flask_fileupload/storage/storage.py
flask_fileupload/storage/utils.py
flask_fileupload/templates/fileupload/base.html
flask_fileupload/templates/fileupload/upload.html
test/__init__.py
test/test_permission.py
test/test_storage.py
