Metadata-Version: 2.1
Name: GC-Flask-FileUpload
Version: 0.5.0
Summary: Flask-FileUpload is a Flask extension for easy file upload and management
Home-page: https://github.com/speedy1991/Flask-FileUpload
Author: Arthur Holzner
Author-email: arthur.holz.91@gmail.com
License: MIT
Platform: any
Classifier: Development Status :: 4 - Beta
Classifier: Environment :: Web Environment
Classifier: Framework :: Flask
Classifier: Intended Audience :: Developers
Classifier: License :: OSI Approved :: MIT License
Classifier: Operating System :: OS Independent
Classifier: Programming Language :: Python
Classifier: Programming Language :: Python :: 3
Classifier: Programming Language :: Python :: 3.4
Classifier: Programming Language :: Python :: 3.5
Classifier: Programming Language :: Python :: 3.6
Classifier: Topic :: Internet :: WWW/HTTP :: Dynamic Content
Classifier: Topic :: Software Development :: Libraries :: Python Modules
Requires-Dist: flask
Requires-Dist: flask-wtf
Requires-Dist: werkzeug
Requires-Dist: flask-login
